[
  {
    "Reporting Date": "01\\/01\\/2026",
    "Incident Number": "INC54180487",
    "Priority": "P4",
    "State": "Closed",
    "Product Line": "Home Lending",
    "Product": "Chase MyHome",
    "App ID": 110010,
    "App": "Chase My Home Advice",
    "Opened Time": "01\\/01\\/2026 12:07",
    "Open Time (Days)": "-",
    "Open Age": "-",
    "Resolved Time": "01\\/06\\/2026 18:20",
    "Time to Resolve (Days)": "5.3",
    "Resolved Age": "4-10 Days",
    "Short Description": "110010 - HLACC Smart fee Secrets Manager-Interactive Role Validation in Non-Prod",
    "Description": "Validate the Secrets Manager-Interactive Role using awsjit in Non-Prod. Steps to be followed: 1. Login on to awsjit using below command  pcl awsjit -t <Snow Ticket\\/Incident> --role-arn <Role ARN> --region=<Region>  2. Use below command to update the Secrets  aws secretsmanager put-secret-value --secret-id=<Customer_Managed_Secret> --secret-string=<Secret_Value> --profile adfsjit  3. Validate the application flow  4. Login to go\\/awsjit - > enter Secrets Manager-Interactive role and snow details and verify if login is successful.",
    "On Behalf Of": "Michael Rodriguez",
    "Opened By": "Robert Johnson",
    "Assignment Group": "CCB_HLT_HLA: Security",
    "Assigned To": "Sarah Chen",
    "Resolved By": "Sarah Chen",
    "Reporting Month": "Jan",
    "Reporting Year": 2026,
    "Owning LOB 1": "CCB",
    "Owning LOB 2": "Home Lending Technology",
    "Owning LOB 3": null,
    "Last Updated Date": "01\\/06\\/26 :",
    "Incident Type": "STANDARD",
    "Category": "Application Software",
    "SubCategory": "Protective \\/ Proactive Measures",
    "Severity": 3,
    "Urgency": "3 - Low",
    "Affected CIs": "Chase My Home Advice - CMHA",
    "Started": "01\\/01\\/26 :",
    "Resolved": "-",
    "Duration": "5 Days 6 Hours 25 Minutes",
    "Detected": "-",
    "Diagnosed": "-",
    "Mitigated": "-",
    "Reopened Time": "-",
    "Paused Time": "-",
    "Business Impact": null,
    "Event Code": null,
    "Sensitive": false,
    "Resolved Time.1": "2026-01-06 18:20:22.000",
    "Executive Summary": "-",
    "Actions Taken": null,
    "Work Notes": "2026-01-01 12:07:00 - Robert Johnson (Work notes)\\nInitial investigation started\\n\\n2026-01-04 03:13:41 - Sarah Chen (Work notes)\\nRoot cause identified - implementing fix\\n\\n2026-01-06 18:20:22 - Sarah Chen (Work notes)\\nFix deployed and validated. Closing ticket.",
    "comments": "\\n\\n2026-01-06 18:20:22 - Sarah Chen (Work notes)\\nIncident resolved per documented runbook.",
    "Close Notes": "110010 - HLACC Smart fee Secrets Manager-Interactive Role Validation in Non-Prod is completed.",
    "Diagnosed Summary": null,
    "Detected Summary": null,
    "Technical Summary": null,
    "Resolved Summary": null,
    "Product Owner": "Patrick Williams",
    "Tech Partner": "Reggie Hansbrough",
    "App TGO": "Home Lending - Chase MyHome",
    "App CTO": "Hansbrough,Reginald",
    "Caused by Change?": "N",
    "Change Number": "-",
    "Problem Number": "-",
    "Problem Cause Code": "-",
    "Problem Short Description": "-",
    "Problem Description": "-",
    "Problem Owning LOB Lvl 1": "-",
    "Problem Owning LOB Lvl 2": "-",
    "Problem Owning LOB Lvl 3": "-"
  },
  {
    "Reporting Date": "01\\/05\\/2026",
    "Incident Number": "INC54180624",
    "Priority": "P2",
    "State": "Closed",
    "Product Line": "Home Lending",
    "Product": "Chase MyHome",
    "App ID": 110010,
    "App": "Chase My Home Advice",
    "Opened Time": "01\\/05\\/2026 03:11",
    "Open Time (Days)": "-",
    "Open Age": "-",
    "Resolved Time": "01\\/06\\/2026 18:12",
    "Time to Resolve (Days)": "1.6",
    "Resolved Age": "1-2 Days",
    "Short Description": "110010 - ChaseMyHome borrower portal login failures - 502 Bad Gateway",
    "Description": "Multiple borrowers reporting 502 Bad Gateway errors when attempting to login to ChaseMyHome borrower portal. Issue intermittent during peak hours 9AM-11AM EST. Initial investigation points to API gateway throttling. Steps: 1. Check API Gateway logs in CloudWatch 2. Verify upstream auth service health 3. Review recent deployment changes 4. Validate certificate expiry on load balancer.",
    "On Behalf Of": "Gehna Malik",
    "Opened By": "Aisha Patel",
    "Assignment Group": "CCB_HLT_HLA: API Team",
    "Assigned To": "Linda Park",
    "Resolved By": "Linda Park",
    "Reporting Month": "Jan",
    "Reporting Year": 2026,
    "Owning LOB 1": "CCB",
    "Owning LOB 2": "Home Lending Technology",
    "Owning LOB 3": null,
    "Last Updated Date": "01\\/06\\/26 :",
    "Incident Type": "INCIDENT",
    "Category": "Application Software",
    "SubCategory": "Performance",
    "Severity": 2,
    "Urgency": "2 - Medium",
    "Affected CIs": "Chase My Home Advice - CMHA",
    "Started": "01\\/05\\/26 :",
    "Resolved": "-",
    "Duration": "1 Days 15 Hours 6 Minutes",
    "Detected": "-",
    "Diagnosed": "-",
    "Mitigated": "-",
    "Reopened Time": "-",
    "Paused Time": "-",
    "Business Impact": "Approximately 4379 customers impacted",
    "Event Code": null,
    "Sensitive": false,
    "Resolved Time.1": "2026-01-06 18:12:13.000",
    "Executive Summary": "P2 incident affecting ChaseMyHome platform - resolved within SLA",
    "Actions Taken": null,
    "Work Notes": "2026-01-05 03:11:00 - Aisha Patel (Work notes)\\nInitial investigation started\\n\\n2026-01-05 22:41:36 - Linda Park (Work notes)\\nRoot cause identified - implementing fix\\n\\n2026-01-06 18:12:13 - Linda Park (Work notes)\\nFix deployed and validated. Closing ticket.",
    "comments": "\\n\\n2026-01-06 18:12:13 - Linda Park (Work notes)\\nIncident resolved per documented runbook.",
    "Close Notes": "110010 - ChaseMyHome borrower portal login failures is completed.",
    "Diagnosed Summary": null,
    "Detected Summary": null,
    "Technical Summary": null,
    "Resolved Summary": null,
    "Product Owner": "Patrick Williams",
    "Tech Partner": "Reggie Hansbrough",
    "App TGO": "Home Lending - Chase MyHome",
    "App CTO": "Hansbrough,Reginald",
    "Caused by Change?": "N",
    "Change Number": "-",
    "Problem Number": "-",
    "Problem Cause Code": "-",
    "Problem Short Description": "-",
    "Problem Description": "-",
    "Problem Owning LOB Lvl 1": "-",
    "Problem Owning LOB Lvl 2": "-",
    "Problem Owning LOB Lvl 3": "-"
  },
  {
    "Reporting Date": "01\\/09\\/2026",
    "Incident Number": "INC54180761",
    "Priority": "P2",
    "State": "Closed",
    "Product Line": "Home Lending",
    "Product": "Chase MyHome",
    "App ID": 110010,
    "App": "Chase My Home Advice",
    "Opened Time": "01\\/09\\/2026 20:25",
    "Open Time (Days)": "-",
    "Open Age": "-",
    "Resolved Time": "01\\/10\\/2026 06:47",
    "Time to Resolve (Days)": "0.4",
    "Resolved Age": "0-1 Days",
    "Short Description": "110010 - MISMO 3.4 XML generation failure for FNMA AUS submission",
    "Description": "Loan submission to Fannie Mae DU failing due to malformed MISMO 3.4 XML. Error: Required field PROPERTY_VALUATION_AMOUNT missing. Affecting ~15 loans per hour. Steps to investigate: 1. Review XML generation service logs 2. Validate appraisal data ingestion 3. Check field mapping configuration 4. Compare with last known good submission template.",
    "On Behalf Of": "Ahmed Hassan",
    "Opened By": "Ahmed Hassan",
    "Assignment Group": "CCB_HLT_HLA: API Team",
    "Assigned To": "Nicole Brown",
    "Resolved By": "Nicole Brown",
    "Reporting Month": "Jan",
    "Reporting Year": 2026,
    "Owning LOB 1": "CCB",
    "Owning LOB 2": "Home Lending Technology",
    "Owning LOB 3": null,
    "Last Updated Date": "01\\/10\\/26 :",
    "Incident Type": "INCIDENT",
    "Category": "Application Software",
    "SubCategory": "Integration Failure",
    "Severity": 2,
    "Urgency": "2 - Medium",
    "Affected CIs": "Chase My Home Advice - CMHA",
    "Started": "01\\/09\\/26 :",
    "Resolved": "-",
    "Duration": "0 Days 10 Hours 9 Minutes",
    "Detected": "-",
    "Diagnosed": "-",
    "Mitigated": "-",
    "Reopened Time": "-",
    "Paused Time": "-",
    "Business Impact": "Approximately 1298 customers impacted",
    "Event Code": null,
    "Sensitive": false,
    "Resolved Time.1": "2026-01-10 06:47:35.000",
    "Executive Summary": "P2 incident affecting ChaseMyHome platform - resolved within SLA",
    "Actions Taken": null,
    "Work Notes": "2026-01-09 20:25:00 - Ahmed Hassan (Work notes)\\nInitial investigation started\\n\\n2026-01-10 01:36:17 - Nicole Brown (Work notes)\\nRoot cause identified - implementing fix\\n\\n2026-01-10 06:47:35 - Nicole Brown (Work notes)\\nFix deployed and validated. Closing ticket.",
    "comments": "\\n\\n2026-01-10 06:47:35 - Nicole Brown (Work notes)\\nIncident resolved per documented runbook.",
    "Close Notes": "110010 - MISMO 3.4 XML generation failure for FNMA AUS submission is completed.",
    "Diagnosed Summary": null,
    "Detected Summary": null,
    "Technical Summary": null,
    "Resolved Summary": null,
    "Product Owner": "Patrick Williams",
    "Tech Partner": "Reggie Hansbrough",
    "App TGO": "Home Lending - Chase MyHome",
    "App CTO": "Hansbrough,Reginald",
    "Caused by Change?": "N",
    "Change Number": "-",
    "Problem Number": "-",
    "Problem Cause Code": "-",
    "Problem Short Description": "-",
    "Problem Description": "-",
    "Problem Owning LOB Lvl 1": "-",
    "Problem Owning LOB Lvl 2": "-",
    "Problem Owning LOB Lvl 3": "-"
  },
  {
    "Reporting Date": "01\\/13\\/2026",
    "Incident Number": "INC54180898",
    "Priority": "P3",
    "State": "Closed",
    "Product Line": "Home Lending",
    "Product": "Chase MyHome",
    "App ID": 110010,
    "App": "Chase My Home Advice",
    "Opened Time": "01\\/13\\/2026 09:34",
    "Open Time (Days)": "-",
    "Open Age": "-",
    "Resolved Time": "01\\/15\\/2026 05:17",
    "Time to Resolve (Days)": "1.8",
    "Resolved Age": "1-2 Days",
    "Short Description": "110010 - Document upload service timeout on ChaseMyHome mobile",
    "Description": "Mobile app users unable to upload supporting documents (W2, paystubs, bank statements). Upload progresses to 90% then times out. Backend S3 service appears healthy. Investigation: 1. Review mobile app network calls 2. Check document processing Lambda timeout settings 3. Validate API Gateway timeout config 4. Review file size limits.",
    "On Behalf Of": "Maria Garcia",
    "Opened By": "Ahmed Hassan",
    "Assignment Group": "CCB_HLT_SENC_HLA: Technician",
    "Assigned To": "James Thompson",
    "Resolved By": "James Thompson",
    "Reporting Month": "Jan",
    "Reporting Year": 2026,
    "Owning LOB 1": "CCB",
    "Owning LOB 2": "Home Lending Technology",
    "Owning LOB 3": null,
    "Last Updated Date": "01\\/15\\/26 :",
    "Incident Type": "INCIDENT",
    "Category": "Application Software",
    "SubCategory": "Mobile Application",
    "Severity": 3,
    "Urgency": "3 - Low",
    "Affected CIs": "Chase My Home Advice - CMHA",
    "Started": "01\\/13\\/26 :",
    "Resolved": "-",
    "Duration": "1 Days 19 Hours 50 Minutes",
    "Detected": "-",
    "Diagnosed": "-",
    "Mitigated": "-",
    "Reopened Time": "-",
    "Paused Time": "-",
    "Business Impact": null,
    "Event Code": null,
    "Sensitive": false,
    "Resolved Time.1": "2026-01-15 05:17:15.000",
    "Executive Summary": "-",
    "Actions Taken": null,
    "Work Notes": "2026-01-13 09:34:00 - Ahmed Hassan (Work notes)\\nInitial investigation started\\n\\n2026-01-14 07:25:37 - James Thompson (Work notes)\\nRoot cause identified - implementing fix\\n\\n2026-01-15 05:17:15 - James Thompson (Work notes)\\nFix deployed and validated. Closing ticket.",
    "comments": "\\n\\n2026-01-15 05:17:15 - James Thompson (Work notes)\\nIncident resolved per documented runbook.",
    "Close Notes": "110010 - Document upload service timeout on ChaseMyHome mobile is completed.",
    "Diagnosed Summary": null,
    "Detected Summary": null,
    "Technical Summary": null,
    "Resolved Summary": null,
    "Product Owner": "Patrick Williams",
    "Tech Partner": "Reggie Hansbrough",
    "App TGO": "Home Lending - Chase MyHome",
    "App CTO": "Hansbrough,Reginald",
    "Caused by Change?": "N",
    "Change Number": "-",
    "Problem Number": "-",
    "Problem Cause Code": "-",
    "Problem Short Description": "-",
    "Problem Description": "-",
    "Problem Owning LOB Lvl 1": "-",
    "Problem Owning LOB Lvl 2": "-",
    "Problem Owning LOB Lvl 3": "-"
  },
  {
    "Reporting Date": "01\\/17\\/2026",
    "Incident Number": "INC54181035",
    "Priority": "P2",
    "State": "Closed",
    "Product Line": "Home Lending",
    "Product": "Chase MyHome",
    "App ID": 110010,
    "App": "Chase My Home Advice",
    "Opened Time": "01\\/17\\/2026 17:06",
    "Open Time (Days)": "-",
    "Open Age": "-",
    "Resolved Time": "01\\/19\\/2026 00:03",
    "Time to Resolve (Days)": "1.3",
    "Resolved Age": "1-2 Days",
    "Short Description": "110010 - Pricing service returning stale rates for prequalification flow",
    "Description": "Borrowers in prequalification flow receiving rates from previous business day. Pricing API cache not invalidating after EOD batch. Impact: 200+ prequalifications with incorrect rate quotes. Required actions: 1. Force cache flush on pricing-svc cluster 2. Review cache TTL configuration 3. Validate EOD batch completion signal 4. Update cache invalidation strategy.",
    "On Behalf Of": "Jennifer Lopez",
    "Opened By": "Aisha Patel",
    "Assignment Group": "CCB_HLT_HLA: API Team",
    "Assigned To": "David Kim",
    "Resolved By": "David Kim",
    "Reporting Month": "Jan",
    "Reporting Year": 2026,
    "Owning LOB 1": "CCB",
    "Owning LOB 2": "Home Lending Technology",
    "Owning LOB 3": null,
    "Last Updated Date": "01\\/19\\/26 :",
    "Incident Type": "INCIDENT",
    "Category": "Application Software",
    "SubCategory": "Data Integrity",
    "Severity": 2,
    "Urgency": "2 - Medium",
    "Affected CIs": "Chase My Home Advice - CMHA",
    "Started": "01\\/17\\/26 :",
    "Resolved": "-",
    "Duration": "1 Days 6 Hours 38 Minutes",
    "Detected": "-",
    "Diagnosed": "-",
    "Mitigated": "-",
    "Reopened Time": "-",
    "Paused Time": "-",
    "Business Impact": "Approximately 89 customers impacted",
    "Event Code": null,
    "Sensitive": false,
    "Resolved Time.1": "2026-01-19 00:03:07.000",
    "Executive Summary": "P2 incident affecting ChaseMyHome platform - resolved within SLA",
    "Actions Taken": null,
    "Work Notes": "2026-01-17 17:06:00 - Aisha Patel (Work notes)\\nInitial investigation started\\n\\n2026-01-18 08:34:33 - David Kim (Work notes)\\nRoot cause identified - implementing fix\\n\\n2026-01-19 00:03:07 - David Kim (Work notes)\\nFix deployed and validated. Closing ticket.",
    "comments": "\\n\\n2026-01-19 00:03:07 - David Kim (Work notes)\\nIncident resolved per documented runbook.",
    "Close Notes": "110010 - Pricing service returning stale rates for prequalification flow is completed.",
    "Diagnosed Summary": null,
    "Detected Summary": null,
    "Technical Summary": null,
    "Resolved Summary": null,
    "Product Owner": "Patrick Williams",
    "Tech Partner": "Reggie Hansbrough",
    "App TGO": "Home Lending - Chase MyHome",
    "App CTO": "Hansbrough,Reginald",
    "Caused by Change?": "N",
    "Change Number": "-",
    "Problem Number": "-",
    "Problem Cause Code": "-",
    "Problem Short Description": "-",
    "Problem Description": "-",
    "Problem Owning LOB Lvl 1": "-",
    "Problem Owning LOB Lvl 2": "-",
    "Problem Owning LOB Lvl 3": "-"
  },
  {
    "Reporting Date": "01\\/21\\/2026",
    "Incident Number": "INC54181172",
    "Priority": "P1",
    "State": "Closed",
    "Product Line": "Home Lending",
    "Product": "Chase MyHome",
    "App ID": 110010,
    "App": "Chase My Home Advice",
    "Opened Time": "01\\/21\\/2026 04:24",
    "Open Time (Days)": "-",
    "Open Age": "-",
    "Resolved Time": "01\\/21\\/2026 07:36",
    "Time to Resolve (Days)": "0.1",
    "Resolved Age": "0-1 Days",
    "Short Description": "110010 - Credit pull integration failure with Equifax API",
    "Description": "Credit bureau integration with Equifax returning HTTP 503 for ~30% of requests over past 2 hours. Issue traced to authentication token rotation. Steps: 1. Verify OAuth token refresh on credit-integration-svc 2. Validate Equifax service health 3. Check for IP allowlist changes 4. Review credentials in Vault.",
    "On Behalf Of": "David Kim",
    "Opened By": "Sarah Chen",
    "Assignment Group": "CCB_HLT_HLA: Frontend",
    "Assigned To": "Sarah Chen",
    "Resolved By": "Sarah Chen",
    "Reporting Month": "Jan",
    "Reporting Year": 2026,
    "Owning LOB 1": "CCB",
    "Owning LOB 2": "Home Lending Technology",
    "Owning LOB 3": null,
    "Last Updated Date": "01\\/21\\/26 :",
    "Incident Type": "INCIDENT",
    "Category": "Application Software",
    "SubCategory": "Third Party Integration",
    "Severity": 1,
    "Urgency": "1 - High",
    "Affected CIs": "Chase My Home Advice - CMHA",
    "Started": "01\\/21\\/26 :",
    "Resolved": "-",
    "Duration": "0 Days 3 Hours 1 Minutes",
    "Detected": "-",
    "Diagnosed": "-",
    "Mitigated": "-",
    "Reopened Time": "-",
    "Paused Time": "-",
    "Business Impact": "Approximately 548 customers impacted",
    "Event Code": null,
    "Sensitive": false,
    "Resolved Time.1": "2026-01-21 07:36:14.000",
    "Executive Summary": "P1 incident affecting ChaseMyHome platform - resolved within SLA",
    "Actions Taken": null,
    "Work Notes": "2026-01-21 04:24:00 - Sarah Chen (Work notes)\\nInitial investigation started\\n\\n2026-01-21 06:00:07 - Sarah Chen (Work notes)\\nRoot cause identified - implementing fix\\n\\n2026-01-21 07:36:14 - Sarah Chen (Work notes)\\nFix deployed and validated. Closing ticket.",
    "comments": "\\n\\n2026-01-21 07:36:14 - Sarah Chen (Work notes)\\nIncident resolved per documented runbook.",
    "Close Notes": "110010 - Credit pull integration failure with Equifax API is completed.",
    "Diagnosed Summary": null,
    "Detected Summary": null,
    "Technical Summary": null,
    "Resolved Summary": null,
    "Product Owner": "Patrick Williams",
    "Tech Partner": "Reggie Hansbrough",
    "App TGO": "Home Lending - Chase MyHome",
    "App CTO": "Hansbrough,Reginald",
    "Caused by Change?": "N",
    "Change Number": "-",
    "Problem Number": "-",
    "Problem Cause Code": "-",
    "Problem Short Description": "-",
    "Problem Description": "-",
    "Problem Owning LOB Lvl 1": "-",
    "Problem Owning LOB Lvl 2": "-",
    "Problem Owning LOB Lvl 3": "-"
  },
  {
    "Reporting Date": "01\\/25\\/2026",
    "Incident Number": "INC54181309",
    "Priority": "P3",
    "State": "Closed",
    "Product Line": "Home Lending",
    "Product": "Chase MyHome",
    "App ID": 110010,
    "App": "Chase My Home Advice",
    "Opened Time": "01\\/25\\/2026 02:29",
    "Open Time (Days)": "-",
    "Open Age": "-",
    "Resolved Time": "01\\/28\\/2026 20:14",
    "Time to Resolve (Days)": "3.7",
    "Resolved Age": "2-4 Days",
    "Short Description": "110010 - Loan dashboard widget rendering blank for premier customers",
    "Description": "Dashboard widget showing loan progress not rendering for customers in 'Premier' segment. JavaScript console shows 'Cannot read property progress of undefined'. Issue introduced in last UI release. Steps: 1. Review recent frontend deployments 2. Check API response for premier segment 3. Validate feature flag configuration 4. Add null safety to component.",
    "On Behalf Of": "James Thompson",
    "Opened By": "Michael Rodriguez",
    "Assignment Group": "CCB_HLT_SENC_HLA: Technician",
    "Assigned To": "James Thompson",
    "Resolved By": "James Thompson",
    "Reporting Month": "Jan",
    "Reporting Year": 2026,
    "Owning LOB 1": "CCB",
    "Owning LOB 2": "Home Lending Technology",
    "Owning LOB 3": null,
    "Last Updated Date": "01\\/28\\/26 :",
    "Incident Type": "INCIDENT",
    "Category": "Application Software",
    "SubCategory": "User Interface",
    "Severity": 3,
    "Urgency": "3 - Low",
    "Affected CIs": "Chase My Home Advice - CMHA",
    "Started": "01\\/25\\/26 :",
    "Resolved": "-",
    "Duration": "3 Days 17 Hours 27 Minutes",
    "Detected": "-",
    "Diagnosed": "-",
    "Mitigated": "-",
    "Reopened Time": "-",
    "Paused Time": "-",
    "Business Impact": null,
    "Event Code": null,
    "Sensitive": false,
    "Resolved Time.1": "2026-01-28 20:14:21.000",
    "Executive Summary": "-",
    "Actions Taken": null,
    "Work Notes": "2026-01-25 02:29:00 - Michael Rodriguez (Work notes)\\nInitial investigation started\\n\\n2026-01-26 23:21:40 - James Thompson (Work notes)\\nRoot cause identified - implementing fix\\n\\n2026-01-28 20:14:21 - James Thompson (Work notes)\\nFix deployed and validated. Closing ticket.",
    "comments": "\\n\\n2026-01-28 20:14:21 - James Thompson (Work notes)\\nIncident resolved per documented runbook.",
    "Close Notes": "110010 - Loan dashboard widget rendering blank for premier customers is completed.",
    "Diagnosed Summary": null,
    "Detected Summary": null,
    "Technical Summary": null,
    "Resolved Summary": null,
    "Product Owner": "Patrick Williams",
    "Tech Partner": "Reggie Hansbrough",
    "App TGO": "Home Lending - Chase MyHome",
    "App CTO": "Hansbrough,Reginald",
    "Caused by Change?": "N",
    "Change Number": "-",
    "Problem Number": "-",
    "Problem Cause Code": "-",
    "Problem Short Description": "-",
    "Problem Description": "-",
    "Problem Owning LOB Lvl 1": "-",
    "Problem Owning LOB Lvl 2": "-",
    "Problem Owning LOB Lvl 3": "-"
  },
  {
    "Reporting Date": "01\\/29\\/2026",
    "Incident Number": "INC54181446",
    "Priority": "P2",
    "State": "Closed",
    "Product Line": "Home Lending",
    "Product": "Chase MyHome",
    "App ID": 110010,
    "App": "Chase My Home Advice",
    "Opened Time": "01\\/29\\/2026 18:22",
    "Open Time (Days)": "-",
    "Open Age": "-",
    "Resolved Time": "01\\/31\\/2026 08:08",
    "Time to Resolve (Days)": "1.6",
    "Resolved Age": "1-2 Days",
    "Short Description": "110010 - Database connection pool exhaustion on home-lending-core",
    "Description": "PostgreSQL connection pool exhausted on home-lending-core RDS instance. Connections at 95% of max_connections (200/210). Application throwing 'too many connections' errors. Steps: 1. Identify long-running queries via pg_stat_activity 2. Kill idle connections > 30min 3. Increase pool size temporarily 4. Review connection leak in loan-search-svc.",
    "On Behalf Of": "Maria Garcia",
    "Opened By": "Robert Johnson",
    "Assignment Group": "CCB_HLT_HLA: API Team",
    "Assigned To": "James Thompson",
    "Resolved By": "James Thompson",
    "Reporting Month": "Jan",
    "Reporting Year": 2026,
    "Owning LOB 1": "CCB",
    "Owning LOB 2": "Home Lending Technology",
    "Owning LOB 3": null,
    "Last Updated Date": "01\\/31\\/26 :",
    "Incident Type": "INCIDENT",
    "Category": "Database",
    "SubCategory": "Capacity",
    "Severity": 2,
    "Urgency": "2 - Medium",
    "Affected CIs": "Chase My Home Advice - CMHA",
    "Started": "01\\/29\\/26 :",
    "Resolved": "-",
    "Duration": "1 Days 13 Hours 49 Minutes",
    "Detected": "-",
    "Diagnosed": "-",
    "Mitigated": "-",
    "Reopened Time": "-",
    "Paused Time": "-",
    "Business Impact": "Approximately 1887 customers impacted",
    "Event Code": null,
    "Sensitive": false,
    "Resolved Time.1": "2026-01-31 08:08:04.000",
    "Executive Summary": "P2 incident affecting ChaseMyHome platform - resolved within SLA",
    "Actions Taken": null,
    "Work Notes": "2026-01-29 18:22:00 - Robert Johnson (Work notes)\\nInitial investigation started\\n\\n2026-01-30 13:15:02 - James Thompson (Work notes)\\nRoot cause identified - implementing fix\\n\\n2026-01-31 08:08:04 - James Thompson (Work notes)\\nFix deployed and validated. Closing ticket.",
    "comments": "\\n\\n2026-01-31 08:08:04 - James Thompson (Work notes)\\nIncident resolved per documented runbook.",
    "Close Notes": "110010 - Database connection pool exhaustion on home-lending-core is completed.",
    "Diagnosed Summary": null,
    "Detected Summary": null,
    "Technical Summary": null,
    "Resolved Summary": null,
    "Product Owner": "Patrick Williams",
    "Tech Partner": "Reggie Hansbrough",
    "App TGO": "Home Lending - Chase MyHome",
    "App CTO": "Hansbrough,Reginald",
    "Caused by Change?": "N",
    "Change Number": "-",
    "Problem Number": "-",
    "Problem Cause Code": "-",
    "Problem Short Description": "-",
    "Problem Description": "-",
    "Problem Owning LOB Lvl 1": "-",
    "Problem Owning LOB Lvl 2": "-",
    "Problem Owning LOB Lvl 3": "-"
  },
  {
    "Reporting Date": "02\\/02\\/2026",
    "Incident Number": "INC54181583",
    "Priority": "P2",
    "State": "Closed",
    "Product Line": "Home Lending",
    "Product": "Chase MyHome",
    "App ID": 110010,
    "App": "Chase My Home Advice",
    "Opened Time": "02\\/02\\/2026 06:30",
    "Open Time (Days)": "-",
    "Open Age": "-",
    "Resolved Time": "02\\/03\\/2026 07:50",
    "Time to Resolve (Days)": "1.1",
    "Resolved Age": "1-2 Days",
    "Short Description": "110010 - Encompass LOS sync delays affecting loan status updates",
    "Description": "Encompass-to-ChaseMyHome sync running 4+ hours behind. Borrowers seeing outdated loan status. Issue with Kafka consumer lag on loan-events topic. Required actions: 1. Scale consumer group from 3 to 6 instances 2. Investigate slow MISMO transformation 3. Review Kafka partition strategy 4. Add lag monitoring alerts.",
    "On Behalf Of": "Ahmed Hassan",
    "Opened By": "Jennifer Lopez",
    "Assignment Group": "CCB_HLT_HLA: Mobile",
    "Assigned To": "Gehna Malik",
    "Resolved By": "Gehna Malik",
    "Reporting Month": "Feb",
    "Reporting Year": 2026,
    "Owning LOB 1": "CCB",
    "Owning LOB 2": "Home Lending Technology",
    "Owning LOB 3": null,
    "Last Updated Date": "02\\/03\\/26 :",
    "Incident Type": "INCIDENT",
    "Category": "Application Software",
    "SubCategory": "Integration Failure",
    "Severity": 2,
    "Urgency": "2 - Medium",
    "Affected CIs": "Chase My Home Advice - CMHA",
    "Started": "02\\/02\\/26 :",
    "Resolved": "-",
    "Duration": "1 Days 1 Hours 49 Minutes",
    "Detected": "-",
    "Diagnosed": "-",
    "Mitigated": "-",
    "Reopened Time": "-",
    "Paused Time": "-",
    "Business Impact": "Approximately 4475 customers impacted",
    "Event Code": null,
    "Sensitive": false,
    "Resolved Time.1": "2026-02-03 07:50:14.000",
    "Executive Summary": "P2 incident affecting ChaseMyHome platform - resolved within SLA",
    "Actions Taken": null,
    "Work Notes": "2026-02-02 06:30:00 - Jennifer Lopez (Work notes)\\nInitial investigation started\\n\\n2026-02-02 19:10:07 - Gehna Malik (Work notes)\\nRoot cause identified - implementing fix\\n\\n2026-02-03 07:50:14 - Gehna Malik (Work notes)\\nFix deployed and validated. Closing ticket.",
    "comments": "\\n\\n2026-02-03 07:50:14 - Gehna Malik (Work notes)\\nIncident resolved per documented runbook.",
    "Close Notes": "110010 - Encompass LOS sync delays affecting loan status updates is completed.",
    "Diagnosed Summary": null,
    "Detected Summary": null,
    "Technical Summary": null,
    "Resolved Summary": null,
    "Product Owner": "Patrick Williams",
    "Tech Partner": "Reggie Hansbrough",
    "App TGO": "Home Lending - Chase MyHome",
    "App CTO": "Hansbrough,Reginald",
    "Caused by Change?": "N",
    "Change Number": "-",
    "Problem Number": "-",
    "Problem Cause Code": "-",
    "Problem Short Description": "-",
    "Problem Description": "-",
    "Problem Owning LOB Lvl 1": "-",
    "Problem Owning LOB Lvl 2": "-",
    "Problem Owning LOB Lvl 3": "-"
  },
  {
    "Reporting Date": "02\\/06\\/2026",
    "Incident Number": "INC54181720",
    "Priority": "P3",
    "State": "Closed",
    "Product Line": "Home Lending",
    "Product": "Chase MyHome",
    "App ID": 110010,
    "App": "Chase My Home Advice",
    "Opened Time": "02\\/06\\/2026 11:41",
    "Open Time (Days)": "-",
    "Open Age": "-",
    "Resolved Time": "02\\/10\\/2026 04:53",
    "Time to Resolve (Days)": "3.7",
    "Resolved Age": "2-4 Days",
    "Short Description": "110010 - ChaseMyHome Advice page intermittent 500 errors",
    "Description": "Chase My Home Advice page returning HTTP 500 for ~5% of requests. Error: NullPointerException in RecommendationEngine.computeOffers(). Affecting customer-facing recommendations. Investigation steps: 1. Review application logs in Splunk 2. Check downstream offer-engine-svc health 3. Validate customer profile data quality 4. Add defensive null checks.",
    "On Behalf Of": "Aisha Patel",
    "Opened By": "David Kim",
    "Assignment Group": "CCB_HLT_HLA: Database",
    "Assigned To": "Aisha Patel",
    "Resolved By": "Aisha Patel",
    "Reporting Month": "Feb",
    "Reporting Year": 2026,
    "Owning LOB 1": "CCB",
    "Owning LOB 2": "Home Lending Technology",
    "Owning LOB 3": null,
    "Last Updated Date": "02\\/10\\/26 :",
    "Incident Type": "INCIDENT",
    "Category": "Application Software",
    "SubCategory": "Application Error",
    "Severity": 3,
    "Urgency": "3 - Low",
    "Affected CIs": "Chase My Home Advice - CMHA",
    "Started": "02\\/06\\/26 :",
    "Resolved": "-",
    "Duration": "3 Days 17 Hours 16 Minutes",
    "Detected": "-",
    "Diagnosed": "-",
    "Mitigated": "-",
    "Reopened Time": "-",
    "Paused Time": "-",
    "Business Impact": null,
    "Event Code": null,
    "Sensitive": false,
    "Resolved Time.1": "2026-02-10 04:53:52.000",
    "Executive Summary": "-",
    "Actions Taken": null,
    "Work Notes": "2026-02-06 11:41:00 - David Kim (Work notes)\\nInitial investigation started\\n\\n2026-02-08 08:17:26 - Aisha Patel (Work notes)\\nRoot cause identified - implementing fix\\n\\n2026-02-10 04:53:52 - Aisha Patel (Work notes)\\nFix deployed and validated. Closing ticket.",
    "comments": "\\n\\n2026-02-10 04:53:52 - Aisha Patel (Work notes)\\nIncident resolved per documented runbook.",
    "Close Notes": "110010 - ChaseMyHome Advice page intermittent 500 errors is completed.",
    "Diagnosed Summary": null,
    "Detected Summary": null,
    "Technical Summary": null,
    "Resolved Summary": null,
    "Product Owner": "Patrick Williams",
    "Tech Partner": "Reggie Hansbrough",
    "App TGO": "Home Lending - Chase MyHome",
    "App CTO": "Hansbrough,Reginald",
    "Caused by Change?": "N",
    "Change Number": "-",
    "Problem Number": "-",
    "Problem Cause Code": "-",
    "Problem Short Description": "-",
    "Problem Description": "-",
    "Problem Owning LOB Lvl 1": "-",
    "Problem Owning LOB Lvl 2": "-",
    "Problem Owning LOB Lvl 3": "-"
  },
  {
    "Reporting Date": "02\\/10\\/2026",
    "Incident Number": "INC54181857",
    "Priority": "P1",
    "State": "Closed",
    "Product Line": "Home Lending",
    "Product": "Chase MyHome",
    "App ID": 110010,
    "App": "Chase My Home Advice",
    "Opened Time": "02\\/10\\/2026 05:54",
    "Open Time (Days)": "-",
    "Open Age": "-",
    "Resolved Time": "02\\/10\\/2026 13:47",
    "Time to Resolve (Days)": "0.3",
    "Resolved Age": "0-1 Days",
    "Short Description": "110010 - eSign DocuSign integration certificate expired",
    "Description": "DocuSign integration for loan disclosure eSigning failing due to expired client certificate. All eSign workflows blocked. Customers unable to complete disclosure signing. Critical action items: 1. Generate new certificate via PKI team 2. Update certificate in DocuSign Admin portal 3. Restart esign-integration-svc 4. Validate end-to-end signing flow.",
    "On Behalf Of": "Aisha Patel",
    "Opened By": "Robert Johnson",
    "Assignment Group": "CCB_HLT_HLA: Mobile",
    "Assigned To": "Michael Rodriguez",
    "Resolved By": "Michael Rodriguez",
    "Reporting Month": "Feb",
    "Reporting Year": 2026,
    "Owning LOB 1": "CCB",
    "Owning LOB 2": "Home Lending Technology",
    "Owning LOB 3": null,
    "Last Updated Date": "02\\/10\\/26 :",
    "Incident Type": "INCIDENT",
    "Category": "Security",
    "SubCategory": "Certificate Management",
    "Severity": 1,
    "Urgency": "1 - High",
    "Affected CIs": "Chase My Home Advice - CMHA",
    "Started": "02\\/10\\/26 :",
    "Resolved": "-",
    "Duration": "0 Days 7 Hours 15 Minutes",
    "Detected": "-",
    "Diagnosed": "-",
    "Mitigated": "-",
    "Reopened Time": "-",
    "Paused Time": "-",
    "Business Impact": "Approximately 2269 customers impacted",
    "Event Code": null,
    "Sensitive": false,
    "Resolved Time.1": "2026-02-10 13:47:42.000",
    "Executive Summary": "P1 incident affecting ChaseMyHome platform - resolved within SLA",
    "Actions Taken": null,
    "Work Notes": "2026-02-10 05:54:00 - Robert Johnson (Work notes)\\nInitial investigation started\\n\\n2026-02-10 09:50:51 - Michael Rodriguez (Work notes)\\nRoot cause identified - implementing fix\\n\\n2026-02-10 13:47:42 - Michael Rodriguez (Work notes)\\nFix deployed and validated. Closing ticket.",
    "comments": "\\n\\n2026-02-10 13:47:42 - Michael Rodriguez (Work notes)\\nIncident resolved per documented runbook.",
    "Close Notes": "110010 - eSign DocuSign integration certificate expired is completed.",
    "Diagnosed Summary": null,
    "Detected Summary": null,
    "Technical Summary": null,
    "Resolved Summary": null,
    "Product Owner": "Patrick Williams",
    "Tech Partner": "Reggie Hansbrough",
    "App TGO": "Home Lending - Chase MyHome",
    "App CTO": "Hansbrough,Reginald",
    "Caused by Change?": "N",
    "Change Number": "-",
    "Problem Number": "-",
    "Problem Cause Code": "-",
    "Problem Short Description": "-",
    "Problem Description": "-",
    "Problem Owning LOB Lvl 1": "-",
    "Problem Owning LOB Lvl 2": "-",
    "Problem Owning LOB Lvl 3": "-"
  },
  {
    "Reporting Date": "02\\/14\\/2026",
    "Incident Number": "INC54181994",
    "Priority": "P2",
    "State": "Closed",
    "Product Line": "Home Lending",
    "Product": "Chase MyHome",
    "App ID": 110010,
    "App": "Chase My Home Advice",
    "Opened Time": "02\\/14\\/2026 22:56",
    "Open Time (Days)": "-",
    "Open Age": "-",
    "Resolved Time": "02\\/15\\/2026 18:33",
    "Time to Resolve (Days)": "0.8",
    "Resolved Age": "0-1 Days",
    "Short Description": "110010 - Appraisal vendor webhook callbacks failing validation",
    "Description": "Webhook callbacks from appraisal vendor (Clear Capital) failing HMAC signature validation. Appraisal status updates not flowing into ChaseMyHome. Approximately 50 appraisals affected. Steps: 1. Verify webhook secret rotation 2. Check vendor-side configuration 3. Validate signature computation logic 4. Replay failed webhooks via DLQ.",
    "On Behalf Of": "Maria Garcia",
    "Opened By": "Steven Lee",
    "Assignment Group": "CCB_HLT_HLA: Database",
    "Assigned To": "Sarah Chen",
    "Resolved By": "Sarah Chen",
    "Reporting Month": "Feb",
    "Reporting Year": 2026,
    "Owning LOB 1": "CCB",
    "Owning LOB 2": "Home Lending Technology",
    "Owning LOB 3": null,
    "Last Updated Date": "02\\/15\\/26 :",
    "Incident Type": "INCIDENT",
    "Category": "Application Software",
    "SubCategory": "Third Party Integration",
    "Severity": 2,
    "Urgency": "2 - Medium",
    "Affected CIs": "Chase My Home Advice - CMHA",
    "Started": "02\\/14\\/26 :",
    "Resolved": "-",
    "Duration": "0 Days 19 Hours 1 Minutes",
    "Detected": "-",
    "Diagnosed": "-",
    "Mitigated": "-",
    "Reopened Time": "-",
    "Paused Time": "-",
    "Business Impact": "Approximately 1614 customers impacted",
    "Event Code": null,
    "Sensitive": false,
    "Resolved Time.1": "2026-02-15 18:33:08.000",
    "Executive Summary": "P2 incident affecting ChaseMyHome platform - resolved within SLA",
    "Actions Taken": null,
    "Work Notes": "2026-02-14 22:56:00 - Steven Lee (Work notes)\\nInitial investigation started\\n\\n2026-02-15 08:44:34 - Sarah Chen (Work notes)\\nRoot cause identified - implementing fix\\n\\n2026-02-15 18:33:08 - Sarah Chen (Work notes)\\nFix deployed and validated. Closing ticket.",
    "comments": "\\n\\n2026-02-15 18:33:08 - Sarah Chen (Work notes)\\nIncident resolved per documented runbook.",
    "Close Notes": "110010 - Appraisal vendor webhook callbacks failing validation is completed.",
    "Diagnosed Summary": null,
    "Detected Summary": null,
    "Technical Summary": null,
    "Resolved Summary": null,
    "Product Owner": "Patrick Williams",
    "Tech Partner": "Reggie Hansbrough",
    "App TGO": "Home Lending - Chase MyHome",
    "App CTO": "Hansbrough,Reginald",
    "Caused by Change?": "N",
    "Change Number": "-",
    "Problem Number": "-",
    "Problem Cause Code": "-",
    "Problem Short Description": "-",
    "Problem Description": "-",
    "Problem Owning LOB Lvl 1": "-",
    "Problem Owning LOB Lvl 2": "-",
    "Problem Owning LOB Lvl 3": "-"
  },
  {
    "Reporting Date": "02\\/18\\/2026",
    "Incident Number": "INC54182131",
    "Priority": "P3",
    "State": "Closed",
    "Product Line": "Home Lending",
    "Product": "Chase MyHome",
    "App ID": 110010,
    "App": "Chase My Home Advice",
    "Opened Time": "02\\/18\\/2026 02:25",
    "Open Time (Days)": "-",
    "Open Age": "-",
    "Resolved Time": "02\\/20\\/2026 14:02",
    "Time to Resolve (Days)": "2.5",
    "Resolved Age": "2-4 Days",
    "Short Description": "110010 - Income verification service slow response - SLA breach",
    "Description": "Income verification service (The Work Number integration) responding 12-15 seconds vs SLA of 3 seconds. Affecting underwriter productivity. Investigation: 1. Profile income-verification-svc latency 2. Review TWN API response times 3. Check for connection pool sizing 4. Implement async pattern for non-blocking calls.",
    "On Behalf Of": "Linda Park",
    "Opened By": "Jennifer Lopez",
    "Assignment Group": "CCB_HLT_HLA: Security",
    "Assigned To": "Jennifer Lopez",
    "Resolved By": "Jennifer Lopez",
    "Reporting Month": "Feb",
    "Reporting Year": 2026,
    "Owning LOB 1": "CCB",
    "Owning LOB 2": "Home Lending Technology",
    "Owning LOB 3": null,
    "Last Updated Date": "02\\/20\\/26 :",
    "Incident Type": "INCIDENT",
    "Category": "Application Software",
    "SubCategory": "Performance",
    "Severity": 3,
    "Urgency": "2 - Medium",
    "Affected CIs": "Chase My Home Advice - CMHA",
    "Started": "02\\/18\\/26 :",
    "Resolved": "-",
    "Duration": "2 Days 11 Hours 54 Minutes",
    "Detected": "-",
    "Diagnosed": "-",
    "Mitigated": "-",
    "Reopened Time": "-",
    "Paused Time": "-",
    "Business Impact": null,
    "Event Code": null,
    "Sensitive": false,
    "Resolved Time.1": "2026-02-20 14:02:40.000",
    "Executive Summary": "-",
    "Actions Taken": null,
    "Work Notes": "2026-02-18 02:25:00 - Jennifer Lopez (Work notes)\\nInitial investigation started\\n\\n2026-02-19 08:13:50 - Jennifer Lopez (Work notes)\\nRoot cause identified - implementing fix\\n\\n2026-02-20 14:02:40 - Jennifer Lopez (Work notes)\\nFix deployed and validated. Closing ticket.",
    "comments": "\\n\\n2026-02-20 14:02:40 - Jennifer Lopez (Work notes)\\nIncident resolved per documented runbook.",
    "Close Notes": "110010 - Income verification service slow response is completed.",
    "Diagnosed Summary": null,
    "Detected Summary": null,
    "Technical Summary": null,
    "Resolved Summary": null,
    "Product Owner": "Patrick Williams",
    "Tech Partner": "Reggie Hansbrough",
    "App TGO": "Home Lending - Chase MyHome",
    "App CTO": "Hansbrough,Reginald",
    "Caused by Change?": "N",
    "Change Number": "-",
    "Problem Number": "-",
    "Problem Cause Code": "-",
    "Problem Short Description": "-",
    "Problem Description": "-",
    "Problem Owning LOB Lvl 1": "-",
    "Problem Owning LOB Lvl 2": "-",
    "Problem Owning LOB Lvl 3": "-"
  },
  {
    "Reporting Date": "02\\/22\\/2026",
    "Incident Number": "INC54182268",
    "Priority": "P3",
    "State": "Closed",
    "Product Line": "Home Lending",
    "Product": "Chase MyHome",
    "App ID": 110010,
    "App": "Chase My Home Advice",
    "Opened Time": "02\\/22\\/2026 13:37",
    "Open Time (Days)": "-",
    "Open Age": "-",
    "Resolved Time": "02\\/24\\/2026 15:50",
    "Time to Resolve (Days)": "2.1",
    "Resolved Age": "2-4 Days",
    "Short Description": "110010 - Property search Maps API quota exceeded",
    "Description": "Google Maps API quota exceeded on property search feature. Map display failing for customers using Property Search. Impact: customer experience degraded. Steps: 1. Increase API quota with vendor 2. Implement client-side caching for repeat searches 3. Review API usage patterns 4. Add quota monitoring/alerting.",
    "On Behalf Of": "Kevin Wu",
    "Opened By": "Nicole Brown",
    "Assignment Group": "CCB_HLT_HLA: DevOps",
    "Assigned To": "Aisha Patel",
    "Resolved By": "Aisha Patel",
    "Reporting Month": "Feb",
    "Reporting Year": 2026,
    "Owning LOB 1": "CCB",
    "Owning LOB 2": "Home Lending Technology",
    "Owning LOB 3": null,
    "Last Updated Date": "02\\/24\\/26 :",
    "Incident Type": "INCIDENT",
    "Category": "Application Software",
    "SubCategory": "Third Party Integration",
    "Severity": 3,
    "Urgency": "3 - Low",
    "Affected CIs": "Chase My Home Advice - CMHA",
    "Started": "02\\/22\\/26 :",
    "Resolved": "-",
    "Duration": "2 Days 2 Hours 47 Minutes",
    "Detected": "-",
    "Diagnosed": "-",
    "Mitigated": "-",
    "Reopened Time": "-",
    "Paused Time": "-",
    "Business Impact": null,
    "Event Code": null,
    "Sensitive": false,
    "Resolved Time.1": "2026-02-24 15:50:33.000",
    "Executive Summary": "-",
    "Actions Taken": null,
    "Work Notes": "2026-02-22 13:37:00 - Nicole Brown (Work notes)\\nInitial investigation started\\n\\n2026-02-23 14:43:46 - Aisha Patel (Work notes)\\nRoot cause identified - implementing fix\\n\\n2026-02-24 15:50:33 - Aisha Patel (Work notes)\\nFix deployed and validated. Closing ticket.",
    "comments": "\\n\\n2026-02-24 15:50:33 - Aisha Patel (Work notes)\\nIncident resolved per documented runbook.",
    "Close Notes": "110010 - Property search Maps API quota exceeded is completed.",
    "Diagnosed Summary": null,
    "Detected Summary": null,
    "Technical Summary": null,
    "Resolved Summary": null,
    "Product Owner": "Patrick Williams",
    "Tech Partner": "Reggie Hansbrough",
    "App TGO": "Home Lending - Chase MyHome",
    "App CTO": "Hansbrough,Reginald",
    "Caused by Change?": "N",
    "Change Number": "-",
    "Problem Number": "-",
    "Problem Cause Code": "-",
    "Problem Short Description": "-",
    "Problem Description": "-",
    "Problem Owning LOB Lvl 1": "-",
    "Problem Owning LOB Lvl 2": "-",
    "Problem Owning LOB Lvl 3": "-"
  },
  {
    "Reporting Date": "02\\/26\\/2026",
    "Incident Number": "INC54182405",
    "Priority": "P2",
    "State": "Closed",
    "Product Line": "Home Lending",
    "Product": "Chase MyHome",
    "App ID": 110010,
    "App": "Chase My Home Advice",
    "Opened Time": "02\\/26\\/2026 04:00",
    "Open Time (Days)": "-",
    "Open Age": "-",
    "Resolved Time": "02\\/26\\/2026 19:36",
    "Time to Resolve (Days)": "0.7",
    "Resolved Age": "0-1 Days",
    "Short Description": "110010 - Loss mitigation workflow stuck for forbearance requests",
    "Description": "Forbearance request workflow stuck in 'Pending Review' state. Camunda BPMN engine not advancing tasks. ~25 customer requests affected. Action items: 1. Review Camunda engine logs 2. Check for stuck process instances 3. Validate task assignment rules 4. Escalate stuck requests manually.",
    "On Behalf Of": "Ahmed Hassan",
    "Opened By": "Ahmed Hassan",
    "Assignment Group": "CCB_HLT_HLA: Security",
    "Assigned To": "Nicole Brown",
    "Resolved By": "Nicole Brown",
    "Reporting Month": "Feb",
    "Reporting Year": 2026,
    "Owning LOB 1": "CCB",
    "Owning LOB 2": "Home Lending Technology",
    "Owning LOB 3": null,
    "Last Updated Date": "02\\/26\\/26 :",
    "Incident Type": "INCIDENT",
    "Category": "Application Software",
    "SubCategory": "Workflow Engine",
    "Severity": 2,
    "Urgency": "2 - Medium",
    "Affected CIs": "Chase My Home Advice - CMHA",
    "Started": "02\\/26\\/26 :",
    "Resolved": "-",
    "Duration": "0 Days 15 Hours 37 Minutes",
    "Detected": "-",
    "Diagnosed": "-",
    "Mitigated": "-",
    "Reopened Time": "-",
    "Paused Time": "-",
    "Business Impact": "Approximately 2425 customers impacted",
    "Event Code": null,
    "Sensitive": false,
    "Resolved Time.1": "2026-02-26 19:36:55.000",
    "Executive Summary": "P2 incident affecting ChaseMyHome platform - resolved within SLA",
    "Actions Taken": null,
    "Work Notes": "2026-02-26 04:00:00 - Ahmed Hassan (Work notes)\\nInitial investigation started\\n\\n2026-02-26 11:48:27 - Nicole Brown (Work notes)\\nRoot cause identified - implementing fix\\n\\n2026-02-26 19:36:55 - Nicole Brown (Work notes)\\nFix deployed and validated. Closing ticket.",
    "comments": "\\n\\n2026-02-26 19:36:55 - Nicole Brown (Work notes)\\nIncident resolved per documented runbook.",
    "Close Notes": "110010 - Loss mitigation workflow stuck for forbearance requests is completed.",
    "Diagnosed Summary": null,
    "Detected Summary": null,
    "Technical Summary": null,
    "Resolved Summary": null,
    "Product Owner": "Patrick Williams",
    "Tech Partner": "Reggie Hansbrough",
    "App TGO": "Home Lending - Chase MyHome",
    "App CTO": "Hansbrough,Reginald",
    "Caused by Change?": "N",
    "Change Number": "-",
    "Problem Number": "-",
    "Problem Cause Code": "-",
    "Problem Short Description": "-",
    "Problem Description": "-",
    "Problem Owning LOB Lvl 1": "-",
    "Problem Owning LOB Lvl 2": "-",
    "Problem Owning LOB Lvl 3": "-"
  },
  {
    "Reporting Date": "03\\/02\\/2026",
    "Incident Number": "INC54182542",
    "Priority": "P2",
    "State": "Closed",
    "Product Line": "Home Lending",
    "Product": "Chase MyHome",
    "App ID": 110010,
    "App": "Chase My Home Advice",
    "Opened Time": "03\\/02\\/2026 01:33",
    "Open Time (Days)": "-",
    "Open Age": "-",
    "Resolved Time": "03\\/02\\/2026 13:21",
    "Time to Resolve (Days)": "0.5",
    "Resolved Age": "0-1 Days",
    "Short Description": "110010 - Session timeout occurring before configured 30 minutes",
    "Description": "Customers reporting session timeouts at 5-10 minutes despite 30-minute configuration. Issue traced to Redis session store eviction policy. Required actions: 1. Review Redis maxmemory-policy 2. Increase session TTL configuration 3. Validate sticky session config on load balancer 4. Add session monitoring metrics.",
    "On Behalf Of": "James Thompson",
    "Opened By": "James Thompson",
    "Assignment Group": "CCB_HLT_HLA: DevOps",
    "Assigned To": "Linda Park",
    "Resolved By": "Linda Park",
    "Reporting Month": "Mar",
    "Reporting Year": 2026,
    "Owning LOB 1": "CCB",
    "Owning LOB 2": "Home Lending Technology",
    "Owning LOB 3": null,
    "Last Updated Date": "03\\/02\\/26 :",
    "Incident Type": "INCIDENT",
    "Category": "Application Software",
    "SubCategory": "Authentication",
    "Severity": 2,
    "Urgency": "2 - Medium",
    "Affected CIs": "Chase My Home Advice - CMHA",
    "Started": "03\\/02\\/26 :",
    "Resolved": "-",
    "Duration": "0 Days 11 Hours 39 Minutes",
    "Detected": "-",
    "Diagnosed": "-",
    "Mitigated": "-",
    "Reopened Time": "-",
    "Paused Time": "-",
    "Business Impact": "Approximately 3766 customers impacted",
    "Event Code": null,
    "Sensitive": false,
    "Resolved Time.1": "2026-03-02 13:21:03.000",
    "Executive Summary": "P2 incident affecting ChaseMyHome platform - resolved within SLA",
    "Actions Taken": null,
    "Work Notes": "2026-03-02 01:33:00 - James Thompson (Work notes)\\nInitial investigation started\\n\\n2026-03-02 07:27:01 - Linda Park (Work notes)\\nRoot cause identified - implementing fix\\n\\n2026-03-02 13:21:03 - Linda Park (Work notes)\\nFix deployed and validated. Closing ticket.",
    "comments": "\\n\\n2026-03-02 13:21:03 - Linda Park (Work notes)\\nIncident resolved per documented runbook.",
    "Close Notes": "110010 - Session timeout occurring before configured 30 minutes is completed.",
    "Diagnosed Summary": null,
    "Detected Summary": null,
    "Technical Summary": null,
    "Resolved Summary": null,
    "Product Owner": "Patrick Williams",
    "Tech Partner": "Reggie Hansbrough",
    "App TGO": "Home Lending - Chase MyHome",
    "App CTO": "Hansbrough,Reginald",
    "Caused by Change?": "N",
    "Change Number": "-",
    "Problem Number": "-",
    "Problem Cause Code": "-",
    "Problem Short Description": "-",
    "Problem Description": "-",
    "Problem Owning LOB Lvl 1": "-",
    "Problem Owning LOB Lvl 2": "-",
    "Problem Owning LOB Lvl 3": "-"
  },
  {
    "Reporting Date": "03\\/06\\/2026",
    "Incident Number": "INC54182679",
    "Priority": "P3",
    "State": "Closed",
    "Product Line": "Home Lending",
    "Product": "Chase MyHome",
    "App ID": 110010,
    "App": "Chase My Home Advice",
    "Opened Time": "03\\/06\\/2026 01:58",
    "Open Time (Days)": "-",
    "Open Age": "-",
    "Resolved Time": "03\\/08\\/2026 05:18",
    "Time to Resolve (Days)": "2.1",
    "Resolved Age": "2-4 Days",
    "Short Description": "110010 - Push notification delivery failure to iOS devices",
    "Description": "Push notifications for loan status updates not being delivered to iOS devices. Android delivery functional. APNs certificate appears valid. Steps: 1. Review notification-svc logs 2. Validate APNs token format 3. Check Apple feedback service for invalid tokens 4. Test with sample iOS device.",
    "On Behalf Of": "James Thompson",
    "Opened By": "Ahmed Hassan",
    "Assignment Group": "CCB_HLT_HLA: ML Platform",
    "Assigned To": "David Kim",
    "Resolved By": "David Kim",
    "Reporting Month": "Mar",
    "Reporting Year": 2026,
    "Owning LOB 1": "CCB",
    "Owning LOB 2": "Home Lending Technology",
    "Owning LOB 3": null,
    "Last Updated Date": "03\\/08\\/26 :",
    "Incident Type": "INCIDENT",
    "Category": "Application Software",
    "SubCategory": "Mobile Application",
    "Severity": 3,
    "Urgency": "3 - Low",
    "Affected CIs": "Chase My Home Advice - CMHA",
    "Started": "03\\/06\\/26 :",
    "Resolved": "-",
    "Duration": "2 Days 3 Hours 34 Minutes",
    "Detected": "-",
    "Diagnosed": "-",
    "Mitigated": "-",
    "Reopened Time": "-",
    "Paused Time": "-",
    "Business Impact": null,
    "Event Code": null,
    "Sensitive": false,
    "Resolved Time.1": "2026-03-08 05:18:45.000",
    "Executive Summary": "-",
    "Actions Taken": null,
    "Work Notes": "2026-03-06 01:58:00 - Ahmed Hassan (Work notes)\\nInitial investigation started\\n\\n2026-03-07 03:38:22 - David Kim (Work notes)\\nRoot cause identified - implementing fix\\n\\n2026-03-08 05:18:45 - David Kim (Work notes)\\nFix deployed and validated. Closing ticket.",
    "comments": "\\n\\n2026-03-08 05:18:45 - David Kim (Work notes)\\nIncident resolved per documented runbook.",
    "Close Notes": "110010 - Push notification delivery failure to iOS devices is completed.",
    "Diagnosed Summary": null,
    "Detected Summary": null,
    "Technical Summary": null,
    "Resolved Summary": null,
    "Product Owner": "Patrick Williams",
    "Tech Partner": "Reggie Hansbrough",
    "App TGO": "Home Lending - Chase MyHome",
    "App CTO": "Hansbrough,Reginald",
    "Caused by Change?": "N",
    "Change Number": "-",
    "Problem Number": "-",
    "Problem Cause Code": "-",
    "Problem Short Description": "-",
    "Problem Description": "-",
    "Problem Owning LOB Lvl 1": "-",
    "Problem Owning LOB Lvl 2": "-",
    "Problem Owning LOB Lvl 3": "-"
  },
  {
    "Reporting Date": "03\\/10\\/2026",
    "Incident Number": "INC54182816",
    "Priority": "P2",
    "State": "Closed",
    "Product Line": "Home Lending",
    "Product": "Chase MyHome",
    "App ID": 110010,
    "App": "Chase My Home Advice",
    "Opened Time": "03\\/10\\/2026 14:23",
    "Open Time (Days)": "-",
    "Open Age": "-",
    "Resolved Time": "03\\/12\\/2026 07:47",
    "Time to Resolve (Days)": "1.7",
    "Resolved Age": "1-2 Days",
    "Short Description": "110010 - Audit log service dropping events under high load",
    "Description": "Audit logging service dropping events when throughput exceeds 5000 events/sec. Compliance risk for regulatory reporting. Required actions: 1. Increase Kafka producer batch size 2. Scale audit-log-consumer to handle backpressure 3. Implement persistent buffer for failed writes 4. Add data quality alerts.",
    "On Behalf Of": "Priya Sharma",
    "Opened By": "Gehna Malik",
    "Assignment Group": "CCB_HLT_HLA: API Team",
    "Assigned To": "Sarah Chen",
    "Resolved By": "Sarah Chen",
    "Reporting Month": "Mar",
    "Reporting Year": 2026,
    "Owning LOB 1": "CCB",
    "Owning LOB 2": "Home Lending Technology",
    "Owning LOB 3": null,
    "Last Updated Date": "03\\/12\\/26 :",
    "Incident Type": "INCIDENT",
    "Category": "Application Software",
    "SubCategory": "Compliance",
    "Severity": 2,
    "Urgency": "1 - High",
    "Affected CIs": "Chase My Home Advice - CMHA",
    "Started": "03\\/10\\/26 :",
    "Resolved": "-",
    "Duration": "1 Days 17 Hours 14 Minutes",
    "Detected": "-",
    "Diagnosed": "-",
    "Mitigated": "-",
    "Reopened Time": "-",
    "Paused Time": "-",
    "Business Impact": "Approximately 4847 customers impacted",
    "Event Code": null,
    "Sensitive": false,
    "Resolved Time.1": "2026-03-12 07:47:28.000",
    "Executive Summary": "P2 incident affecting ChaseMyHome platform - resolved within SLA",
    "Actions Taken": null,
    "Work Notes": "2026-03-10 14:23:00 - Gehna Malik (Work notes)\\nInitial investigation started\\n\\n2026-03-11 11:05:14 - Sarah Chen (Work notes)\\nRoot cause identified - implementing fix\\n\\n2026-03-12 07:47:28 - Sarah Chen (Work notes)\\nFix deployed and validated. Closing ticket.",
    "comments": "\\n\\n2026-03-12 07:47:28 - Sarah Chen (Work notes)\\nIncident resolved per documented runbook.",
    "Close Notes": "110010 - Audit log service dropping events under high load is completed.",
    "Diagnosed Summary": null,
    "Detected Summary": null,
    "Technical Summary": null,
    "Resolved Summary": null,
    "Product Owner": "Patrick Williams",
    "Tech Partner": "Reggie Hansbrough",
    "App TGO": "Home Lending - Chase MyHome",
    "App CTO": "Hansbrough,Reginald",
    "Caused by Change?": "N",
    "Change Number": "-",
    "Problem Number": "-",
    "Problem Cause Code": "-",
    "Problem Short Description": "-",
    "Problem Description": "-",
    "Problem Owning LOB Lvl 1": "-",
    "Problem Owning LOB Lvl 2": "-",
    "Problem Owning LOB Lvl 3": "-"
  },
  {
    "Reporting Date": "03\\/14\\/2026",
    "Incident Number": "INC54182953",
    "Priority": "P2",
    "State": "Closed",
    "Product Line": "Home Lending",
    "Product": "Chase MyHome",
    "App ID": 110010,
    "App": "Chase My Home Advice",
    "Opened Time": "03\\/14\\/2026 13:41",
    "Open Time (Days)": "-",
    "Open Age": "-",
    "Resolved Time": "03\\/15\\/2026 18:45",
    "Time to Resolve (Days)": "1.2",
    "Resolved Age": "1-2 Days",
    "Short Description": "110010 - Disclosure document PDF generation memory leak",
    "Description": "PDF generation service experiencing OOM kills every 6 hours. Heap dump shows iText library not releasing document objects. Affecting Loan Estimate and Closing Disclosure generation. Steps: 1. Apply memory leak fix in pdf-generation-svc 2. Increase JVM heap to 4GB temporarily 3. Add proactive restart at 80% heap utilization 4. Plan iText upgrade.",
    "On Behalf Of": "Ahmed Hassan",
    "Opened By": "Sarah Chen",
    "Assignment Group": "CCB_HLT_HLA: ML Platform",
    "Assigned To": "Nicole Brown",
    "Resolved By": "Nicole Brown",
    "Reporting Month": "Mar",
    "Reporting Year": 2026,
    "Owning LOB 1": "CCB",
    "Owning LOB 2": "Home Lending Technology",
    "Owning LOB 3": null,
    "Last Updated Date": "03\\/15\\/26 :",
    "Incident Type": "INCIDENT",
    "Category": "Application Software",
    "SubCategory": "Memory Management",
    "Severity": 2,
    "Urgency": "2 - Medium",
    "Affected CIs": "Chase My Home Advice - CMHA",
    "Started": "03\\/14\\/26 :",
    "Resolved": "-",
    "Duration": "1 Days 5 Hours 26 Minutes",
    "Detected": "-",
    "Diagnosed": "-",
    "Mitigated": "-",
    "Reopened Time": "-",
    "Paused Time": "-",
    "Business Impact": "Approximately 4507 customers impacted",
    "Event Code": null,
    "Sensitive": false,
    "Resolved Time.1": "2026-03-15 18:45:30.000",
    "Executive Summary": "P2 incident affecting ChaseMyHome platform - resolved within SLA",
    "Actions Taken": null,
    "Work Notes": "2026-03-14 13:41:00 - Sarah Chen (Work notes)\\nInitial investigation started\\n\\n2026-03-15 04:13:15 - Nicole Brown (Work notes)\\nRoot cause identified - implementing fix\\n\\n2026-03-15 18:45:30 - Nicole Brown (Work notes)\\nFix deployed and validated. Closing ticket.",
    "comments": "\\n\\n2026-03-15 18:45:30 - Nicole Brown (Work notes)\\nIncident resolved per documented runbook.",
    "Close Notes": "110010 - Disclosure document PDF generation memory leak is completed.",
    "Diagnosed Summary": null,
    "Detected Summary": null,
    "Technical Summary": null,
    "Resolved Summary": null,
    "Product Owner": "Patrick Williams",
    "Tech Partner": "Reggie Hansbrough",
    "App TGO": "Home Lending - Chase MyHome",
    "App CTO": "Hansbrough,Reginald",
    "Caused by Change?": "N",
    "Change Number": "-",
    "Problem Number": "-",
    "Problem Cause Code": "-",
    "Problem Short Description": "-",
    "Problem Description": "-",
    "Problem Owning LOB Lvl 1": "-",
    "Problem Owning LOB Lvl 2": "-",
    "Problem Owning LOB Lvl 3": "-"
  },
  {
    "Reporting Date": "03\\/18\\/2026",
    "Incident Number": "INC54183090",
    "Priority": "P2",
    "State": "Closed",
    "Product Line": "Home Lending",
    "Product": "Chase MyHome",
    "App ID": 110010,
    "App": "Chase My Home Advice",
    "Opened Time": "03\\/18\\/2026 02:03",
    "Open Time (Days)": "-",
    "Open Age": "-",
    "Resolved Time": "03\\/19\\/2026 00:05",
    "Time to Resolve (Days)": "0.9",
    "Resolved Age": "0-1 Days",
    "Short Description": "110010 - Rate lock service - duplicate locks created for same loan",
    "Description": "Race condition in rate-lock-svc creating duplicate locks for same loan ID. Customers seeing two confirmation emails. Data integrity issue. Investigation: 1. Identify all duplicate locks via SQL query 2. Implement distributed lock with Redis 3. Add idempotency key to API 4. Reconcile pricing impact.",
    "On Behalf Of": "Maria Garcia",
    "Opened By": "Maria Garcia",
    "Assignment Group": "CCB_HLT_HLA: Security",
    "Assigned To": "Linda Park",
    "Resolved By": "Linda Park",
    "Reporting Month": "Mar",
    "Reporting Year": 2026,
    "Owning LOB 1": "CCB",
    "Owning LOB 2": "Home Lending Technology",
    "Owning LOB 3": null,
    "Last Updated Date": "03\\/19\\/26 :",
    "Incident Type": "INCIDENT",
    "Category": "Application Software",
    "SubCategory": "Data Integrity",
    "Severity": 2,
    "Urgency": "2 - Medium",
    "Affected CIs": "Chase My Home Advice - CMHA",
    "Started": "03\\/18\\/26 :",
    "Resolved": "-",
    "Duration": "0 Days 22 Hours 7 Minutes",
    "Detected": "-",
    "Diagnosed": "-",
    "Mitigated": "-",
    "Reopened Time": "-",
    "Paused Time": "-",
    "Business Impact": "Approximately 501 customers impacted",
    "Event Code": null,
    "Sensitive": false,
    "Resolved Time.1": "2026-03-19 00:05:17.000",
    "Executive Summary": "P2 incident affecting ChaseMyHome platform - resolved within SLA",
    "Actions Taken": null,
    "Work Notes": "2026-03-18 02:03:00 - Maria Garcia (Work notes)\\nInitial investigation started\\n\\n2026-03-18 13:04:08 - Linda Park (Work notes)\\nRoot cause identified - implementing fix\\n\\n2026-03-19 00:05:17 - Linda Park (Work notes)\\nFix deployed and validated. Closing ticket.",
    "comments": "\\n\\n2026-03-19 00:05:17 - Linda Park (Work notes)\\nIncident resolved per documented runbook.",
    "Close Notes": "110010 - Rate lock service is completed.",
    "Diagnosed Summary": null,
    "Detected Summary": null,
    "Technical Summary": null,
    "Resolved Summary": null,
    "Product Owner": "Patrick Williams",
    "Tech Partner": "Reggie Hansbrough",
    "App TGO": "Home Lending - Chase MyHome",
    "App CTO": "Hansbrough,Reginald",
    "Caused by Change?": "N",
    "Change Number": "-",
    "Problem Number": "-",
    "Problem Cause Code": "-",
    "Problem Short Description": "-",
    "Problem Description": "-",
    "Problem Owning LOB Lvl 1": "-",
    "Problem Owning LOB Lvl 2": "-",
    "Problem Owning LOB Lvl 3": "-"
  },
  {
    "Reporting Date": "03\\/22\\/2026",
    "Incident Number": "INC54183227",
    "Priority": "P3",
    "State": "Closed",
    "Product Line": "Home Lending",
    "Product": "Chase MyHome",
    "App ID": 110010,
    "App": "Chase My Home Advice",
    "Opened Time": "03\\/22\\/2026 14:05",
    "Open Time (Days)": "-",
    "Open Age": "-",
    "Resolved Time": "03\\/26\\/2026 04:37",
    "Time to Resolve (Days)": "3.6",
    "Resolved Age": "2-4 Days",
    "Short Description": "110010 - Property valuation AVM model returning $0 for new construction",
    "Description": "AVM (Automated Valuation Model) returning $0 valuations for newly constructed properties. ML model not handling sparse comparable sales data. Affecting prequalification accuracy. Steps: 1. Add fallback logic when AVM confidence < threshold 2. Route new construction to human appraisal 3. Retrain model with new construction features 4. Notify affected customers.",
    "On Behalf Of": "Aisha Patel",
    "Opened By": "Priya Sharma",
    "Assignment Group": "CCB_HLT_SENC_HLA: Technician",
    "Assigned To": "David Kim",
    "Resolved By": "David Kim",
    "Reporting Month": "Mar",
    "Reporting Year": 2026,
    "Owning LOB 1": "CCB",
    "Owning LOB 2": "Home Lending Technology",
    "Owning LOB 3": null,
    "Last Updated Date": "03\\/26\\/26 :",
    "Incident Type": "INCIDENT",
    "Category": "Application Software",
    "SubCategory": "Machine Learning",
    "Severity": 3,
    "Urgency": "2 - Medium",
    "Affected CIs": "Chase My Home Advice - CMHA",
    "Started": "03\\/22\\/26 :",
    "Resolved": "-",
    "Duration": "3 Days 14 Hours 57 Minutes",
    "Detected": "-",
    "Diagnosed": "-",
    "Mitigated": "-",
    "Reopened Time": "-",
    "Paused Time": "-",
    "Business Impact": null,
    "Event Code": null,
    "Sensitive": false,
    "Resolved Time.1": "2026-03-26 04:37:58.000",
    "Executive Summary": "-",
    "Actions Taken": null,
    "Work Notes": "2026-03-22 14:05:00 - Priya Sharma (Work notes)\\nInitial investigation started\\n\\n2026-03-24 09:21:29 - David Kim (Work notes)\\nRoot cause identified - implementing fix\\n\\n2026-03-26 04:37:58 - David Kim (Work notes)\\nFix deployed and validated. Closing ticket.",
    "comments": "\\n\\n2026-03-26 04:37:58 - David Kim (Work notes)\\nIncident resolved per documented runbook.",
    "Close Notes": "110010 - Property valuation AVM model returning $0 for new construction is completed.",
    "Diagnosed Summary": null,
    "Detected Summary": null,
    "Technical Summary": null,
    "Resolved Summary": null,
    "Product Owner": "Patrick Williams",
    "Tech Partner": "Reggie Hansbrough",
    "App TGO": "Home Lending - Chase MyHome",
    "App CTO": "Hansbrough,Reginald",
    "Caused by Change?": "N",
    "Change Number": "-",
    "Problem Number": "-",
    "Problem Cause Code": "-",
    "Problem Short Description": "-",
    "Problem Description": "-",
    "Problem Owning LOB Lvl 1": "-",
    "Problem Owning LOB Lvl 2": "-",
    "Problem Owning LOB Lvl 3": "-"
  },
  {
    "Reporting Date": "03\\/26\\/2026",
    "Incident Number": "INC54183364",
    "Priority": "P1",
    "State": "Closed",
    "Product Line": "Home Lending",
    "Product": "Chase MyHome",
    "App ID": 110010,
    "App": "Chase My Home Advice",
    "Opened Time": "03\\/26\\/2026 15:22",
    "Open Time (Days)": "-",
    "Open Age": "-",
    "Resolved Time": "03\\/26\\/2026 19:26",
    "Time to Resolve (Days)": "0.2",
    "Resolved Age": "0-1 Days",
    "Short Description": "110010 - SAML SSO redirect loop for internal users",
    "Description": "Internal users (loan officers, underwriters) experiencing SAML SSO redirect loops when accessing ChaseMyHome admin portal. Issue post-IDP upgrade. Critical for operations. Action items: 1. Validate new IDP metadata 2. Check SAML attribute mapping 3. Review session cookie SameSite setting 4. Coordinate with IAM team.",
    "On Behalf Of": "Steven Lee",
    "Opened By": "Nicole Brown",
    "Assignment Group": "CCB_HLT_HLA: Frontend",
    "Assigned To": "Jennifer Lopez",
    "Resolved By": "Jennifer Lopez",
    "Reporting Month": "Mar",
    "Reporting Year": 2026,
    "Owning LOB 1": "CCB",
    "Owning LOB 2": "Home Lending Technology",
    "Owning LOB 3": null,
    "Last Updated Date": "03\\/26\\/26 :",
    "Incident Type": "INCIDENT",
    "Category": "Security",
    "SubCategory": "Authentication",
    "Severity": 1,
    "Urgency": "1 - High",
    "Affected CIs": "Chase My Home Advice - CMHA",
    "Started": "03\\/26\\/26 :",
    "Resolved": "-",
    "Duration": "0 Days 4 Hours 30 Minutes",
    "Detected": "-",
    "Diagnosed": "-",
    "Mitigated": "-",
    "Reopened Time": "-",
    "Paused Time": "-",
    "Business Impact": "Approximately 1440 customers impacted",
    "Event Code": null,
    "Sensitive": false,
    "Resolved Time.1": "2026-03-26 19:26:41.000",
    "Executive Summary": "P1 incident affecting ChaseMyHome platform - resolved within SLA",
    "Actions Taken": null,
    "Work Notes": "2026-03-26 15:22:00 - Nicole Brown (Work notes)\\nInitial investigation started\\n\\n2026-03-26 17:24:20 - Jennifer Lopez (Work notes)\\nRoot cause identified - implementing fix\\n\\n2026-03-26 19:26:41 - Jennifer Lopez (Work notes)\\nFix deployed and validated. Closing ticket.",
    "comments": "\\n\\n2026-03-26 19:26:41 - Jennifer Lopez (Work notes)\\nIncident resolved per documented runbook.",
    "Close Notes": "110010 - SAML SSO redirect loop for internal users is completed.",
    "Diagnosed Summary": null,
    "Detected Summary": null,
    "Technical Summary": null,
    "Resolved Summary": null,
    "Product Owner": "Patrick Williams",
    "Tech Partner": "Reggie Hansbrough",
    "App TGO": "Home Lending - Chase MyHome",
    "App CTO": "Hansbrough,Reginald",
    "Caused by Change?": "N",
    "Change Number": "-",
    "Problem Number": "-",
    "Problem Cause Code": "-",
    "Problem Short Description": "-",
    "Problem Description": "-",
    "Problem Owning LOB Lvl 1": "-",
    "Problem Owning LOB Lvl 2": "-",
    "Problem Owning LOB Lvl 3": "-"
  },
  {
    "Reporting Date": "03\\/30\\/2026",
    "Incident Number": "INC54183501",
    "Priority": "P3",
    "State": "Closed",
    "Product Line": "Home Lending",
    "Product": "Chase MyHome",
    "App ID": 110010,
    "App": "Chase My Home Advice",
    "Opened Time": "03\\/30\\/2026 11:18",
    "Open Time (Days)": "-",
    "Open Age": "-",
    "Resolved Time": "03\\/31\\/2026 21:43",
    "Time to Resolve (Days)": "1.4",
    "Resolved Age": "1-2 Days",
    "Short Description": "110010 - Escrow calculation rounding error - $0.01 discrepancy",
    "Description": "Escrow calculation showing $0.01 rounding discrepancy in monthly payment breakdown. Compliance concern under RESPA. Affecting approx 500 loans displayed values. Required actions: 1. Implement BigDecimal with HALF_EVEN rounding 2. Audit historical calculations 3. Validate against servicing system 4. Issue customer communications if needed.",
    "On Behalf Of": "Gehna Malik",
    "Opened By": "Priya Sharma",
    "Assignment Group": "CCB_HLT_HLA: API Team",
    "Assigned To": "Gehna Malik",
    "Resolved By": "Gehna Malik",
    "Reporting Month": "Mar",
    "Reporting Year": 2026,
    "Owning LOB 1": "CCB",
    "Owning LOB 2": "Home Lending Technology",
    "Owning LOB 3": null,
    "Last Updated Date": "03\\/31\\/26 :",
    "Incident Type": "INCIDENT",
    "Category": "Application Software",
    "SubCategory": "Compliance",
    "Severity": 3,
    "Urgency": "2 - Medium",
    "Affected CIs": "Chase My Home Advice - CMHA",
    "Started": "03\\/30\\/26 :",
    "Resolved": "-",
    "Duration": "1 Days 10 Hours 3 Minutes",
    "Detected": "-",
    "Diagnosed": "-",
    "Mitigated": "-",
    "Reopened Time": "-",
    "Paused Time": "-",
    "Business Impact": null,
    "Event Code": null,
    "Sensitive": false,
    "Resolved Time.1": "2026-03-31 21:43:50.000",
    "Executive Summary": "-",
    "Actions Taken": null,
    "Work Notes": "2026-03-30 11:18:00 - Priya Sharma (Work notes)\\nInitial investigation started\\n\\n2026-03-31 04:30:55 - Gehna Malik (Work notes)\\nRoot cause identified - implementing fix\\n\\n2026-03-31 21:43:50 - Gehna Malik (Work notes)\\nFix deployed and validated. Closing ticket.",
    "comments": "\\n\\n2026-03-31 21:43:50 - Gehna Malik (Work notes)\\nIncident resolved per documented runbook.",
    "Close Notes": "110010 - Escrow calculation rounding error is completed.",
    "Diagnosed Summary": null,
    "Detected Summary": null,
    "Technical Summary": null,
    "Resolved Summary": null,
    "Product Owner": "Patrick Williams",
    "Tech Partner": "Reggie Hansbrough",
    "App TGO": "Home Lending - Chase MyHome",
    "App CTO": "Hansbrough,Reginald",
    "Caused by Change?": "N",
    "Change Number": "-",
    "Problem Number": "-",
    "Problem Cause Code": "-",
    "Problem Short Description": "-",
    "Problem Description": "-",
    "Problem Owning LOB Lvl 1": "-",
    "Problem Owning LOB Lvl 2": "-",
    "Problem Owning LOB Lvl 3": "-"
  },
  {
    "Reporting Date": "04\\/03\\/2026",
    "Incident Number": "INC54183638",
    "Priority": "P2",
    "State": "Closed",
    "Product Line": "Home Lending",
    "Product": "Chase MyHome",
    "App ID": 110010,
    "App": "Chase My Home Advice",
    "Opened Time": "04\\/03\\/2026 05:00",
    "Open Time (Days)": "-",
    "Open Age": "-",
    "Resolved Time": "04\\/04\\/2026 22:57",
    "Time to Resolve (Days)": "1.7",
    "Resolved Age": "1-2 Days",
    "Short Description": "110010 - Chatbot intent classifier accuracy degraded post-model update",
    "Description": "Customer service chatbot intent classification accuracy dropped from 92% to 67% after weekly model retrain. Customers being routed to wrong agents. Steps: 1. Rollback to previous model version 2. Investigate training data drift 3. Add model performance monitoring 4. Implement A/B testing for model deployments.",
    "On Behalf Of": "Robert Johnson",
    "Opened By": "Aisha Patel",
    "Assignment Group": "CCB_HLT_HLA: Security",
    "Assigned To": "Jennifer Lopez",
    "Resolved By": "Jennifer Lopez",
    "Reporting Month": "Apr",
    "Reporting Year": 2026,
    "Owning LOB 1": "CCB",
    "Owning LOB 2": "Home Lending Technology",
    "Owning LOB 3": null,
    "Last Updated Date": "04\\/04\\/26 :",
    "Incident Type": "INCIDENT",
    "Category": "Application Software",
    "SubCategory": "Machine Learning",
    "Severity": 2,
    "Urgency": "2 - Medium",
    "Affected CIs": "Chase My Home Advice - CMHA",
    "Started": "04\\/03\\/26 :",
    "Resolved": "-",
    "Duration": "1 Days 17 Hours 57 Minutes",
    "Detected": "-",
    "Diagnosed": "-",
    "Mitigated": "-",
    "Reopened Time": "-",
    "Paused Time": "-",
    "Business Impact": "Approximately 1313 customers impacted",
    "Event Code": null,
    "Sensitive": false,
    "Resolved Time.1": "2026-04-04 22:57:47.000",
    "Executive Summary": "P2 incident affecting ChaseMyHome platform - resolved within SLA",
    "Actions Taken": null,
    "Work Notes": "2026-04-03 05:00:00 - Aisha Patel (Work notes)\\nInitial investigation started\\n\\n2026-04-04 01:58:53 - Jennifer Lopez (Work notes)\\nRoot cause identified - implementing fix\\n\\n2026-04-04 22:57:47 - Jennifer Lopez (Work notes)\\nFix deployed and validated. Closing ticket.",
    "comments": "\\n\\n2026-04-04 22:57:47 - Jennifer Lopez (Work notes)\\nIncident resolved per documented runbook.",
    "Close Notes": "110010 - Chatbot intent classifier accuracy degraded post-model update is completed.",
    "Diagnosed Summary": null,
    "Detected Summary": null,
    "Technical Summary": null,
    "Resolved Summary": null,
    "Product Owner": "Patrick Williams",
    "Tech Partner": "Reggie Hansbrough",
    "App TGO": "Home Lending - Chase MyHome",
    "App CTO": "Hansbrough,Reginald",
    "Caused by Change?": "N",
    "Change Number": "-",
    "Problem Number": "-",
    "Problem Cause Code": "-",
    "Problem Short Description": "-",
    "Problem Description": "-",
    "Problem Owning LOB Lvl 1": "-",
    "Problem Owning LOB Lvl 2": "-",
    "Problem Owning LOB Lvl 3": "-"
  },
  {
    "Reporting Date": "04\\/07\\/2026",
    "Incident Number": "INC54183775",
    "Priority": "P2",
    "State": "Closed",
    "Product Line": "Home Lending",
    "Product": "Chase MyHome",
    "App ID": 110010,
    "App": "Chase My Home Advice",
    "Opened Time": "04\\/07\\/2026 18:31",
    "Open Time (Days)": "-",
    "Open Age": "-",
    "Resolved Time": "04\\/08\\/2026 19:15",
    "Time to Resolve (Days)": "1.0",
    "Resolved Age": "1-2 Days",
    "Short Description": "110010 - Data warehouse ETL job failure - daily reporting impacted",
    "Description": "Nightly ETL job to data warehouse failed with 'transaction log full' error. Daily executive reports unavailable. Investigation: 1. Truncate transaction log on warehouse DB 2. Review ETL job for long-running transactions 3. Implement incremental load strategy 4. Add transaction log monitoring.",
    "On Behalf Of": "Steven Lee",
    "Opened By": "James Thompson",
    "Assignment Group": "CCB_HLT_HLA: Mobile",
    "Assigned To": "Aisha Patel",
    "Resolved By": "Aisha Patel",
    "Reporting Month": "Apr",
    "Reporting Year": 2026,
    "Owning LOB 1": "CCB",
    "Owning LOB 2": "Home Lending Technology",
    "Owning LOB 3": null,
    "Last Updated Date": "04\\/08\\/26 :",
    "Incident Type": "INCIDENT",
    "Category": "Database",
    "SubCategory": "ETL",
    "Severity": 2,
    "Urgency": "2 - Medium",
    "Affected CIs": "Chase My Home Advice - CMHA",
    "Started": "04\\/07\\/26 :",
    "Resolved": "-",
    "Duration": "1 Days 0 Hours 43 Minutes",
    "Detected": "-",
    "Diagnosed": "-",
    "Mitigated": "-",
    "Reopened Time": "-",
    "Paused Time": "-",
    "Business Impact": "Approximately 2003 customers impacted",
    "Event Code": null,
    "Sensitive": false,
    "Resolved Time.1": "2026-04-08 19:15:45.000",
    "Executive Summary": "P2 incident affecting ChaseMyHome platform - resolved within SLA",
    "Actions Taken": null,
    "Work Notes": "2026-04-07 18:31:00 - James Thompson (Work notes)\\nInitial investigation started\\n\\n2026-04-08 06:53:22 - Aisha Patel (Work notes)\\nRoot cause identified - implementing fix\\n\\n2026-04-08 19:15:45 - Aisha Patel (Work notes)\\nFix deployed and validated. Closing ticket.",
    "comments": "\\n\\n2026-04-08 19:15:45 - Aisha Patel (Work notes)\\nIncident resolved per documented runbook.",
    "Close Notes": "110010 - Data warehouse ETL job failure is completed.",
    "Diagnosed Summary": null,
    "Detected Summary": null,
    "Technical Summary": null,
    "Resolved Summary": null,
    "Product Owner": "Patrick Williams",
    "Tech Partner": "Reggie Hansbrough",
    "App TGO": "Home Lending - Chase MyHome",
    "App CTO": "Hansbrough,Reginald",
    "Caused by Change?": "N",
    "Change Number": "-",
    "Problem Number": "-",
    "Problem Cause Code": "-",
    "Problem Short Description": "-",
    "Problem Description": "-",
    "Problem Owning LOB Lvl 1": "-",
    "Problem Owning LOB Lvl 2": "-",
    "Problem Owning LOB Lvl 3": "-"
  }
]